pyabcranger.cpython-38-darwin.so
pyabcranger-0.0.72.dist-info/RECORD
pyabcranger-0.0.72.dist-info/LICENSE
pyabcranger-0.0.72.dist-info/WHEEL
pyabcranger-0.0.72.dist-info/top_level.txt
pyabcranger-0.0.72.dist-info/METADATA
