Metadata-Version: 2.1
Name: pyabcranger
Version: 0.0.72
Summary: ABC random forests for model choice and parameter estimation, python wrapper
Home-page: https://github.com/diyabc/abcranger
Author: François-David Collin
Author-email: fradav@gmail.com
License: MIT License
License-File: LICENSE
